cu_fynan/__init__.py
cu_fynan/__main__.py
cu_fynan/calculation.py
cu_fynan-0.1.3.dist-info/METADATA
cu_fynan-0.1.3.dist-info/WHEEL
cu_fynan-0.1.3.dist-info/top_level.txt
cu_fynan-0.1.3.dist-info/RECORD
