Metadata-Version: 2.1
Name: cu_fynan
Version: 0.1.3
Summary: Application for analyse of financial data
Author-email: Savva Serebriakov <savva08savva08@gmail.com>
License: MIT
Requires-Python: >=3.8
